{
	"credit": "Made with Blockbench",
	"textures": {
		"0": "crystaldiv:blocks/base_rune",
		"particle": "crystaldiv:blocks/base_rune"
	},
	"elements": [
		{
			"from": [0, 0, 0.1],
			"to": [16, 16, 0.1],
			"faces": {
				"north": {"uv": [0, 0, 16, 16], "texture": "#0"},
				"east": {"uv": [0, 0, 0, 0], "texture": "#0"},
				"south": {"uv": [0, 0, 16, 16], "texture": "#0"},
				"west": {"uv": [0, 0, 0, 0], "texture": "#0"},
				"up": {"uv": [0, 0, 0, 0], "texture": "#0"},
				"down": {"uv": [0, 0, 0, 0], "texture": "#0"}
			}
		},
		{
			"from": [2, 2, 1],
			"to": [14, 14, 1],
			"faces": {
				"north": {"uv": [0, 0, 16, 16], "texture": "#0"},
				"east": {"uv": [0, 0, 0, 0], "texture": "#0"},
				"south": {"uv": [0, 0, 16, 16], "texture": "#0"},
				"west": {"uv": [0, 0, 0, 0], "texture": "#0"},
				"up": {"uv": [0, 0, 0, 0], "texture": "#0"},
				"down": {"uv": [0, 0, 0, 0], "texture": "#0"}
			}
		}
	],
	"display": {
		"thirdperson_righthand": {
			"rotation": [-60, 0, 0],
			"translation": [0, 2.25, 0.5],
			"scale": [0.4, 0.4, 0.4]
		},
		"thirdperson_lefthand": {
			"rotation": [-60, 0, 0],
			"translation": [0, 2.25, 0.5],
			"scale": [0.4, 0.4, 0.4]
		},
		"firstperson_righthand": {
			"translation": [12, -6, 0]
		},
		"firstperson_lefthand": {
			"translation": [12, -6, 0]
		},
		"ground": {
			"rotation": [-90, 0, 0],
			"translation": [0, 1.25, 0],
			"scale": [0.5, 0.5, 0.5]
		},
		"gui": {
			"rotation": [0, -180, 0]
		},
		"head": {
			"rotation": [-90, 0, 0],
			"translation": [0, 15, 0]
		},
		"fixed": {
			"rotation": [0, -180, 0],
			"translation": [0, 0, -9]
		}
	},
	"groups": [
		{
			"name": "VoxelShapes",
			"origin": [8, 8, 8],
			"children": []
		}, 0, 1]
}